flake8-toml-config-injector.pth
flake8_toml_config/__init__.py
flake8_toml_config/_compat.py
flake8_toml_config/config.py
flake8_toml_config/py.typed
flake8_toml_config-1.0.0.dist-info/LICENSE.txt
flake8_toml_config-1.0.0.dist-info/METADATA
flake8_toml_config-1.0.0.dist-info/WHEEL
flake8_toml_config-1.0.0.dist-info/RECORD
