Metadata-Version: 2.3
Name: flake8-toml-config
Version: 1.0.0
Summary: Configure flake8 via pyproject.toml. Supports local plugins.
License: MIT
Author: Kurt McKee
Author-email: contactme@kurtmckee.org
Requires-Python: >=3.9
Classifier: License :: OSI Approved :: MIT License
Classifier: Programming Language :: Python :: 3
Classifier: Programming Language :: Python :: 3.9
Classifier: Programming Language :: Python :: 3.10
Classifier: Programming Language :: Python :: 3.11
Classifier: Programming Language :: Python :: 3.12
Classifier: Programming Language :: Python :: 3.13
Requires-Dist: flake8 (>=7.0.0)
